headers/__init__.py
headers/http.py
headers/mail.py
headers/mime.py
headers/netnews.py
py_message_headers-2021.7.5.dist-info/LICENSE
py_message_headers-2021.7.5.dist-info/METADATA
py_message_headers-2021.7.5.dist-info/WHEEL
py_message_headers-2021.7.5.dist-info/top_level.txt
py_message_headers-2021.7.5.dist-info/RECORD
