Metadata-Version: 2.1
Name: py-message-headers
Version: 2021.7.5
Summary: Constants for IANA message headers (http, mime, mail, etc) 
Home-page: https://github.com/kirsn/py-message-headers
Author: Kiran S
Author-email: kirsn@yahoo.com
License: UNKNOWN
Platform: UNKNOWN
Classifier: Programming Language :: Python
Classifier: Programming Language :: Python :: 3
Classifier: License :: OSI Approved :: MIT License
Classifier: Operating System :: OS Independent
Classifier: Intended Audience :: Developers
License-File: LICENSE
